felicette/__init__.py
felicette/cli.py
felicette/constants.py
felicette/sat_downloader.py
felicette/sat_processor.py
felicette/utils/__init__.py
felicette/utils/color.py
felicette/utils/file_manager.py
felicette/utils/gdal_pansharpen.py
felicette/utils/geo_utils.py
felicette/utils/image_processing_utils.py
felicette/utils/sys_utils.py
felicette-0.1.13.dist-info/LICENSE
felicette-0.1.13.dist-info/METADATA
felicette-0.1.13.dist-info/WHEEL
felicette-0.1.13.dist-info/entry_points.txt
felicette-0.1.13.dist-info/top_level.txt
felicette-0.1.13.dist-info/RECORD
